CHANGELOG
LICENSE
MANIFEST.in
MIGRATION
Makefile
README.rst
dev-requirements.txt
requirements.txt
setup.cfg
setup.py
tox.ini
docs/Makefile
docs/api.rst
docs/conf.py
docs/contents.rst.inc
docs/foreword.rst
docs/index.rst
docs/installation.rst
docs/license.rst
docs/locale.rst
docs/make.bat
docs/quickstart.rst
docs/tryton_module_api.rst
docs/tutorial.rst
docs/versionmanagement.rst
docs/_static/favicon.png
docs/_static/logo.png
docs/_templates/sidebarintro.html
nereid/__init__.py
nereid/application.py
nereid/caching.py
nereid/config.py
nereid/csrf.py
nereid/ctx.py
nereid/exceptions.py
nereid/globals.py
nereid/helpers.py
nereid/logging.py
nereid/routing.py
nereid/session.py
nereid/sessions.py
nereid/signals.py
nereid/templating.py
nereid/testing.py
nereid/wrappers.py
nereid/contrib/__init__.py
nereid/contrib/locale.py
nereid/contrib/pagination.py
nereid/contrib/sitemap.py
nereid/tests/__init__.py
nereid/tests/test_dispatch.py
nereid/tests/test_helpers.py
nereid/tests/test_pagination.py
nereid/tests/test_signals.py
nereid/tests/test_templates.py
nereid_test_module/README.rst
nereid_test_module/__init__.py
nereid_test_module/model.py
nereid_test_module/tryton.cfg
nereid_test_module/templates/registration.jinja
nereid_test_module/templates/tests/from-module.html
nereid_test_module/templates/tests/test-changing-context.html
nereid_test_module/templates/tests/translation-test.html
tests/__init__.py
trytond_nereid/__init__.py
trytond_nereid/babel.cfg
trytond_nereid/configuration.py
trytond_nereid/configuration.xml
trytond_nereid/country.py
trytond_nereid/currency.py
trytond_nereid/i18n.py
trytond_nereid/locale.xml
trytond_nereid/model.py
trytond_nereid/party.py
trytond_nereid/party.xml
trytond_nereid/static_file.py
trytond_nereid/static_file.xml
trytond_nereid/translation.py
trytond_nereid/translation.xml
trytond_nereid/trigger.xml
trytond_nereid/tryton.cfg
trytond_nereid/user.py
trytond_nereid/website.py
trytond_nereid.egg-info/PKG-INFO
trytond_nereid.egg-info/SOURCES.txt
trytond_nereid.egg-info/dependency_links.txt
trytond_nereid.egg-info/entry_points.txt
trytond_nereid.egg-info/not-zip-safe
trytond_nereid.egg-info/requires.txt
trytond_nereid.egg-info/top_level.txt
trytond_nereid/locale/ca_ES.po
trytond_nereid/locale/de_DE.po
