Metadata-Version: 1.1
Name: trytond-nereid
Version: 4.0.1.6
Summary: Tryton - Web Framework
Home-page: http://www.fulfil.io
Author: Fulfil.IO
Author-email: support@fulfil.io
License: BSD
Platform: any
Classifier: Development Status :: 4 - Beta
Classifier: Environment :: Web Environment
Classifier: Intended Audience :: Developers
Classifier: License :: OSI Approved :: BSD License
Classifier: Operating System :: OS Independent
Classifier: Programming Language :: Python
Classifier: Framework :: Tryton
Classifier: Topic :: Internet :: WWW/HTTP :: Dynamic Content
Classifier: Topic :: Software Development :: Libraries :: Python Modules
